bau/__init__.py
bau/c.py
bau/pkgconfig.py
bau/rule.py
bau/util.py
bau-0.1.data/scripts/bau
bau-0.1.dist-info/LICENSE
bau-0.1.dist-info/METADATA
bau-0.1.dist-info/WHEEL
bau-0.1.dist-info/top_level.txt
bau-0.1.dist-info/RECORD
